any_auth/LOGGER_NAME
any_auth/VERSION
any_auth/__init__.py
any_auth/api/__init__.py
any_auth/api/aks.py
any_auth/api/auth.py
any_auth/api/org_mem_ras.py
any_auth/api/org_mems.py
any_auth/api/orgs.py
any_auth/api/proj_aks.py
any_auth/api/proj_aks_ras.py
any_auth/api/proj_mem_ras.py
any_auth/api/proj_mems.py
any_auth/api/projs.py
any_auth/api/ras.py
any_auth/api/roles.py
any_auth/api/root.py
any_auth/api/users.py
any_auth/api/verify.py
any_auth/app.py
any_auth/backend/__init__.py
any_auth/backend/_base.py
any_auth/backend/_client.py
any_auth/backend/api_keys.py
any_auth/backend/organization_members.py
any_auth/backend/organizations.py
any_auth/backend/project_members.py
any_auth/backend/projects.py
any_auth/backend/role_assignments.py
any_auth/backend/roles.py
any_auth/backend/settings.py
any_auth/backend/users.py
any_auth/build_app.py
any_auth/config.py
any_auth/deps/__init__.py
any_auth/deps/app_state.py
any_auth/deps/auth.py
any_auth/deps/role_assignment.py
any_auth/logger_name.py
any_auth/types/__init__.py
any_auth/types/api_key.py
any_auth/types/auth.py
any_auth/types/organization.py
any_auth/types/organization_member.py
any_auth/types/pagination.py
any_auth/types/project.py
any_auth/types/project_member.py
any_auth/types/role.py
any_auth/types/role_assignment.py
any_auth/types/roles.yml
any_auth/types/token_.py
any_auth/types/user.py
any_auth/utils/__init__.py
any_auth/utils/auth.py
any_auth/utils/dummy_cache.py
any_auth/utils/exception_handlers.py
any_auth/utils/is_.py
any_auth/utils/jwt_manager.py
any_auth/utils/to_.py
any_auth/version.py
any_auth-0.3.0.dist-info/LICENSE
any_auth-0.3.0.dist-info/METADATA
any_auth-0.3.0.dist-info/WHEEL
any_auth-0.3.0.dist-info/RECORD
