Metadata-Version: 2.3
Name: any-auth
Version: 0.3.0
Summary: An Any-Auth, A Essential Auth Lib.
License: MIT
Author: Allen Chou
Author-email: f1470891079@gmail.com
Requires-Python: >=3.11,<4.0
Classifier: License :: OSI Approved :: MIT License
Classifier: Programming Language :: Python :: 3
Classifier: Programming Language :: Python :: 3.11
Classifier: Programming Language :: Python :: 3.12
Classifier: Programming Language :: Python :: 3.13
Provides-Extra: all
Requires-Dist: authlib
Requires-Dist: bcrypt
Requires-Dist: diskcache
Requires-Dist: fastapi[standard]
Requires-Dist: fastapi_mail
Requires-Dist: itsdangerous
Requires-Dist: logging-bullet-train
Requires-Dist: pydantic-settings
Requires-Dist: pydantic[email,timezone]
Requires-Dist: pyjwt
Requires-Dist: pymongo[srv]
Requires-Dist: redis
Project-URL: Homepage, https://github.com/allen2c/any-auth
